flet_page_manager/__init__.py
flet_page_manager/exception.py
flet_page_manager/manager.py
flet_page_manager/pages/__init__.py
flet_page_manager/pages/base.py
fletpagemanager-0.1.1.dist-info/METADATA
fletpagemanager-0.1.1.dist-info/WHEEL
fletpagemanager-0.1.1.dist-info/RECORD
